README.rst
setup.cfg
setup.py
ambisafe/HMAC.py
ambisafe/__init__.py
ambisafe/account.py
ambisafe/auth.py
ambisafe/client.py
ambisafe/containers.py
ambisafe/crypt.py
ambisafe/exc.py
ambisafe/transactions.py
ambisafe.egg-info/PKG-INFO
ambisafe.egg-info/SOURCES.txt
ambisafe.egg-info/dependency_links.txt
ambisafe.egg-info/requires.txt
ambisafe.egg-info/top_level.txt
test/__init__.py
test/test.py