Metadata-Version: 1.1
Name: ambisafe
Version: 0.28.2
Summary: Ambisafe KeyServer client library
Home-page: https://bitbucket.org/ambisafe/client-python
Author: Anton Simernia
Author-email: anton.simernia@ambisafe.co
License: UNKNOWN
Download-URL: https://bitbucket.org/ambisafe/client-python/get/v0.28.2.zip
Keywords: ambisafe,bitcoin
Platform: UNKNOWN
Classifier: Intended Audience :: Developers
